winui3/_winui3_microsoft_ui_xaml_resources.cp312-win_arm64.pyd
winui3/_winui3_microsoft_ui_xaml_resources.pyi
winui3/microsoft/ui/xaml/resources/__init__.py
winui3/microsoft/ui/xaml/resources/py.typed
winui3_microsoft_ui_xaml_resources-3.2.1.dist-info/METADATA
winui3_microsoft_ui_xaml_resources-3.2.1.dist-info/WHEEL
winui3_microsoft_ui_xaml_resources-3.2.1.dist-info/top_level.txt
winui3_microsoft_ui_xaml_resources-3.2.1.dist-info/RECORD
